UiLibrary/__init__.py
UiLibrary/test.py
UiLibrary/ui.py
UiLibrary-1.0.3.dist-info/METADATA
UiLibrary-1.0.3.dist-info/WHEEL
UiLibrary-1.0.3.dist-info/top_level.txt
UiLibrary-1.0.3.dist-info/RECORD
