Metadata-Version: 2.1
Name: UiLibrary
Version: 1.0.3
Summary: A gui development library
Home-page: https://github.com/Andre-cmd-rgb/Py-Ui-Library
Author: Andre-Cmd-Rgb
Author-email: andreavigolini@outlook.com
License: MIT
Keywords: Py Ui Library
Platform: UNKNOWN
